Workbook

Sheet Guía de Uso
A1: AGROMACK | B1: Kit Avícola Profesional — Sistema de Gestión y Costeo
A3: CALCULADORA INTEGRAL AVÍCOLA
A4: Planifica, costea y proyecta tu producción avícola en minutos — postura, cría y venta, o ciclo completo.
A6: 📂 ¿QUÉ INCLUYE ESTE KIT?
A7: Datos Técnicos | B7: Parámetros de referencia por línea genética (Hy-Line, Lohmann): curvas de postura, consumo de alimento y mortalidad. Alimenta automáticamente los 3 módulos de cálculo.
A8: Postura | B8: Compra de gallinas listas para poner. Calcula inversión, dimensionamiento e ingresos hasta la pelecha (24 meses).
A9: Cría y Venta | B9: Compra de pollitas de 1 día para vender como pollonas listas para postura. Ideal para negocios de recría.
A10: Ciclo Completo | B10: Cría desde pollita de 1 día hasta el final de la etapa de postura. Vista integral del negocio completo.
A11: Dashboard | B11: Resumen ejecutivo con los KPI clave de los 3 modos de operación y gráfico comparativo, actualizado en tiempo real.
A13: ⚙️ CÓMO USAR ESTA CALCULADORA
A14: Paso 1 | B14: Ve a la hoja "Datos Técnicos" y confirma o ajusta los parámetros técnicos de tu línea genética (opcional, ya vienen precargados).
A15: Paso 2 | B15: Elige el módulo que se ajusta a tu negocio: "Postura", "Cría y Venta" o "Ciclo Completo".
A16: Paso 3 | B16: Ingresa tus datos en las celdas AZULES (número de aves, precios, costos). El resto se calcula solo.
A17: Paso 4 | B17: Revisa el flujo mensual proyectado: verde = flujo acumulado positivo, rojo = aún en déficit.
A18: Paso 5 | B18: Ve al "Dashboard" para comparar los 3 modos y decidir cuál conviene más a tu proyecto.
A20: 🎨 CÓDIGO DE COLORES
A21: Celda azul | B21: Dato editable: aquí ingresas tus propios números (precios, cantidades, costos).
A22: Celda verde clara | B22: Cálculo técnico automático (consumo, área, equipos). No requiere edición.
A23: Fila verde | B23: Flujo de caja acumulado positivo: el proyecto ya recuperó la inversión.
A24: Fila roja | B24: Flujo de caja acumulado negativo: el proyecto aún no recupera la inversión.
A26: 💡 RECOMENDACIONES
A27: • | B27: Usa precios y costos actualizados de tu zona para proyecciones realistas.
A28: • | B28: Las curvas Lohmann son aproximaciones conservadoras (ver hoja Datos Técnicos).
A29: • | B29: Este kit es una herramienta de apoyo a la decisión; valida los resultados con tu propia experiencia de campo.
A31: AGROMACK | B31: www.agromack.cl · contacto@agromack.cl · Versión 1.0

Sheet Dashboard
A1: AGROMACK | C1: Kit Avícola Profesional
A3: DASHBOARD COMPARATIVO — 3 MODOS DE OPERACIÓN
A4: Resumen ejecutivo enlazado a los módulos de cálculo. Se actualiza automáticamente al cambiar los supuestos en cada hoja.
A6: Indicador | B6: Postura | C6: Cría y Venta | D6: Ciclo Completo
A7: Inversión inicial ($) | B7: =Postura!B37 -> 9631.6 | C7: ='Cría y Venta'!B26 -> 3500 | D7: ='Ciclo Completo'!B35 -> 6981.6
A8: Ingreso total proyectado ($) | B8: =SUM(Postura!E43:E66) -> 28888.346 | C8: ='Cría y Venta'!B40 -> 3088.169 | D8: =SUM('Ciclo Completo'!F45:F68) -> 27449.875
A9: Costo operativo total ($) | B9: =SUM(Postura!J43:J66) -> 19812.966 | C9: =SUM('Cría y Venta'!E31:F36) -> 1618.1009 | D9: =SUM('Ciclo Completo'!G41:G68) -> 20294.84
A10: Flujo acumulado final ($) | B10: =Postura!L66 -> -556.2205 | C10: ='Cría y Venta'!I36 -> -2029.9319 | D10: ='Ciclo Completo'!I68 -> 173.43506
A11: Margen sobre inversión (%) | B11: =B10/B7 -> -0.057749544 | C11: =C10/C7 -> -0.57998055 | D11: =D10/D7 -> 0.024841736
A12: Periodo de recuperación | B12: {=IFERROR("Mes "&INDEX(Postura!A43:A66,MATCH(TRUE,Postura!L43:L66>=0,0)),"Fuera del periodo")} -> Mes 19 | C12: {=IFERROR("Sem "&INDEX('Cría y Venta'!B31:B36,MATCH(TRUE,'Cría y Venta'!I31:I36>=0,0)),"Fuera del periodo")} -> Fuera del periodo | D12: {=IFERROR("Mes "&INDEX('Ciclo Completo'!A41:A68,MATCH(TRUE,'Ciclo Completo'!I41:I68>=0,0)),"Fuera del periodo")} -> Mes 19

Sheet Postura
A1: AGROMACK | G1: Kit Avícola Profesional · Sistema de Gestión y Costeo
A2: CALCULADORA AVÍCOLA — MODO POSTURA
A3: Compra de gallinas listas para poner → operar hasta la pelecha
A5: DATOS DEL PROYECTO | D5: LÍNEA GENÉTICA (ingresa 1, 2, 3 o 4)
A6: Número de aves | B6: 500 | D6: 1=Hy-Line Brown · 2=Lohmann Brown · 3=Hy-Line W-36 · 4=Lohmann LSL
A7: Precio gallina lista / unidad | B7: 6.5 | D7: Línea seleccionada | E7: 1
A8: Precio venta huevo / unidad | B8: 0.12 | D8: Sistema (1=Piso, 2=Jaula, 3=Semi-pastoreo) | E8: 1
A9: Precio alimento postura / kg | B9: 0.5 | D9: Comedero (1=Tolva, 2=Lineal) | E9: 1
A10: Costo construcción / m² | B10: 80 | D10: Bebedero (1=Nipple, 2=Campana, 3=Canal) | E10: 1
A11: Infraestructura adicional (monto fijo) | B11: 500 | D11: Precio unitario comedero | E11: 18
A12: Vida útil infraestructura (meses) | B12: 120 | D12: Precio unitario bebedero | E12: 1.2
A13: Mano de obra mensual | B13: 0 | D13: Precio unitario nido | E13: 15
A14: Otros costos mensuales | B14: 0
A15: Reposición aves (%/mes) | B15: 0
A16: Meses a proyectar | B16: 24
A17: Ingresa tus valores en las celdas azules
A19: DIMENSIONAMIENTO TÉCNICO
A20: Consumo alimento g/ave/día | B20: =INDEX('Datos Técnicos'!D12:D15,E7) -> 115
A21: Ratio agua:alimento | B21: =INDEX('Datos Técnicos'!E12:E15,E7) -> 1.8
A22: m²/ave según sistema | B22: =IF(E8=1,INDEX('Datos Técnicos'!F12:F15,E7),IF(E8=2,INDEX('Datos Técnicos'!G12:G15,E7),INDEX('Datos Técnicos'!H12:H15,E7))) -> 0.1
A23: Área requerida (m²) | B23: =B6*B22 -> 50
A24: Alimento diario (kg) | B24: =B6*B20/1000 -> 57.5
A25: Alimento mensual (kg) | B25: =B24*'Datos Técnicos'!B5 -> 1748
A26: Agua diaria (L) | B26: =B24*B21 -> 103.5
A27: Comederos requeridos | B27: =IF(E9=1,CEILING(B6/INDEX('Datos Técnicos'!K12:K15,E7),1),CEILING(B6*INDEX('Datos Técnicos'!J12:J15,E7)/100,1)) -> 17
A28: Bebederos requeridos | B28: =IF(E10=1,CEILING(B6/INDEX('Datos Técnicos'!L12:L15,E7),1),IF(E10=2,CEILING(B6/INDEX('Datos Técnicos'!M12:M15,E7),1),CEILING(B6*INDEX('Datos Técnicos'!N12:N15,E7)/100,1))) -> 63
A29: Nidos requeridos | B29: =CEILING(B6/INDEX('Datos Técnicos'!O12:O15,E7),1) -> 100
A31: INVERSIÓN INICIAL
A32: Costo aves | B32: =B6*B7 -> 3250
A33: Costo infraestructura | B33: =B23*B10+B11 -> 4500
A34: Costo comederos | B34: =B27*E11 -> 306
A35: Costo bebederos | B35: =B28*E12 -> 75.6
A36: Costo nidos | B36: =B29*E13 -> 1500
A37: TOTAL INVERSIÓN INICIAL | B37: =SUM(B32:B36) -> 9631.6
A38: Depreciación mensual infra | B38: =B33/B12 -> 37.5
A40: FLUJO MENSUAL PROYECTADO
A41: La inversión se descuenta del flujo acumulado desde el mes 1. Mortalidad 0.5%/mes.
A42: Mes | B42: Aves productivas | C42: Postura % | D42: Huevos | E42: Ingresos | F42: Alimento kg | G42: Costo alim. | H42: Otros costos | I42: Reposición | J42: Egresos op. | K42: Flujo neto | L42: Flujo acumulado
A43: 1 | B43: =B6 -> 500 | C43: =INDEX('Datos Técnicos'!B20:Y23,E7,1)/100 -> 0.62 | D43: =B43*C43*'Datos Técnicos'!B5 -> 9424 | E43: =D43*B8 -> 1130.88 | F43: =B43*B20/1000*'Datos Técnicos'!B5 -> 1748 | G43: =F43*B9 -> 874 | H43: =B13+B14 -> 0 | I43: 0 | J43: =G43+H43+I43 -> 874 | K43: =E43-J43 -> 256.88 | L43: =-B37+K43 -> -9374.72
A44: 2 | B44: =B6*(1-'Datos Técnicos'!B6)^1 -> 497.5 | C44: =INDEX('Datos Técnicos'!B20:Y23,E7,2)/100 -> 0.92 | D44: =B44*C44*'Datos Técnicos'!B5 -> 13914.08 | E44: =D44*B8 -> 1669.6896 | F44: =B44*B20/1000*'Datos Técnicos'!B5 -> 1739.26 | G44: =F44*B9 -> 869.63 | H44: =B13+B14 -> 0 | I44: =IF(B15>0,B6*B15*B7,0) -> 0 | J44: =G44+H44+I44 -> 869.63 | K44: =E44-J44 -> 800.0596 | L44: =L43+K44 -> -8574.6604
A45: 3 | B45: =B6*(1-'Datos Técnicos'!B6)^2 -> 495.0125 | C45: =INDEX('Datos Técnicos'!B20:Y23,E7,3)/100 -> 0.95 | D45: =B45*C45*'Datos Técnicos'!B5 -> 14295.961 | E45: =D45*B8 -> 1715.5153 | F45: =B45*B20/1000*'Datos Técnicos'!B5 -> 1730.5637 | G45: =F45*B9 -> 865.28185 | H45: =B13+B14 -> 0 | I45: =IF(B15>0,B6*B15*B7,0) -> 0 | J45: =G45+H45+I45 -> 865.28185 | K45: =E45-J45 -> 850.23347 | L45: =L44+K45 -> -7724.4269
A46: 4 | B46: =B6*(1-'Datos Técnicos'!B6)^3 -> 492.53744 | C46: =INDEX('Datos Técnicos'!B20:Y23,E7,4)/100 -> 0.95 | D46: =B46*C46*'Datos Técnicos'!B5 -> 14224.481 | E46: =D46*B8 -> 1706.9377 | F46: =B46*B20/1000*'Datos Técnicos'!B5 -> 1721.9109 | G46: =F46*B9 -> 860.95544 | H46: =B13+B14 -> 0 | I46: =IF(B15>0,B6*B15*B7,0) -> 0 | J46: =G46+H46+I46 -> 860.95544 | K46: =E46-J46 -> 845.9823 | L46: =L45+K46 -> -6878.4446
A47: 5 | B47: =B6*(1-'Datos Técnicos'!B6)^4 -> 490.07475 | C47: =INDEX('Datos Técnicos'!B20:Y23,E7,5)/100 -> 0.94 | D47: =B47*C47*'Datos Técnicos'!B5 -> 14004.376 | E47: =D47*B8 -> 1680.5251 | F47: =B47*B20/1000*'Datos Técnicos'!B5 -> 1713.3013 | G47: =F47*B9 -> 856.65066 | H47: =B13+B14 -> 0 | I47: =IF(B15>0,B6*B15*B7,0) -> 0 | J47: =G47+H47+I47 -> 856.65066 | K47: =E47-J47 -> 823.87446 | L47: =L46+K47 -> -6054.5702
A48: 6 | B48: =B6*(1-'Datos Técnicos'!B6)^5 -> 487.62438 | C48: =INDEX('Datos Técnicos'!B20:Y23,E7,6)/100 -> 0.93 | D48: =B48*C48*'Datos Técnicos'!B5 -> 13786.116 | E48: =D48*B8 -> 1654.334 | F48: =B48*B20/1000*'Datos Técnicos'!B5 -> 1704.7348 | G48: =F48*B9 -> 852.36741 | H48: =B13+B14 -> 0 | I48: =IF(B15>0,B6*B15*B7,0) -> 0 | J48: =G48+H48+I48 -> 852.36741 | K48: =E48-J48 -> 801.96655 | L48: =L47+K48 -> -5252.6036
A49: 7 | B49: =B6*(1-'Datos Técnicos'!B6)^6 -> 485.18625 | C49: =INDEX('Datos Técnicos'!B20:Y23,E7,7)/100 -> 0.91 | D49: =B49*C49*'Datos Técnicos'!B5 -> 13422.193 | E49: =D49*B8 -> 1610.6631 | F49: =B49*B20/1000*'Datos Técnicos'!B5 -> 1696.2111 | G49: =F49*B9 -> 848.10557 | H49: =B13+B14 -> 0 | I49: =IF(B15>0,B6*B15*B7,0) -> 0 | J49: =G49+H49+I49 -> 848.10557 | K49: =E49-J49 -> 762.55753 | L49: =L48+K49 -> -4490.0461
A50: 8 | B50: =B6*(1-'Datos Técnicos'!B6)^7 -> 482.76032 | C50: =INDEX('Datos Técnicos'!B20:Y23,E7,8)/100 -> 0.89 | D50: =B50*C50*'Datos Técnicos'!B5 -> 13061.563 | E50: =D50*B8 -> 1567.3876 | F50: =B50*B20/1000*'Datos Técnicos'!B5 -> 1687.7301 | G50: =F50*B9 -> 843.86505 | H50: =B13+B14 -> 0 | I50: =IF(B15>0,B6*B15*B7,0) -> 0 | J50: =G50+H50+I50 -> 843.86505 | K50: =E50-J50 -> 723.52255 | L50: =L49+K50 -> -3766.5235
A51: 9 | B51: =B6*(1-'Datos Técnicos'!B6)^8 -> 480.34652 | C51: =INDEX('Datos Técnicos'!B20:Y23,E7,9)/100 -> 0.86 | D51: =B51*C51*'Datos Técnicos'!B5 -> 12558.179 | E51: =D51*B8 -> 1506.9815 | F51: =B51*B20/1000*'Datos Técnicos'!B5 -> 1679.2914 | G51: =F51*B9 -> 839.64572 | H51: =B13+B14 -> 0 | I51: =IF(B15>0,B6*B15*B7,0) -> 0 | J51: =G51+H51+I51 -> 839.64572 | K51: =E51-J51 -> 667.33582 | L51: =L50+K51 -> -3099.1877
A52: 10 | B52: =B6*(1-'Datos Técnicos'!B6)^9 -> 477.94479 | C52: =INDEX('Datos Técnicos'!B20:Y23,E7,10)/100 -> 0.83 | D52: =B52*C52*'Datos Técnicos'!B5 -> 12059.503 | E52: =D52*B8 -> 1447.1404 | F52: =B52*B20/1000*'Datos Técnicos'!B5 -> 1670.895 | G52: =F52*B9 -> 835.44749 | H52: =B13+B14 -> 0 | I52: =IF(B15>0,B6*B15*B7,0) -> 0 | J52: =G52+H52+I52 -> 835.44749 | K52: =E52-J52 -> 611.69286 | L52: =L51+K52 -> -2487.4948
A53: 11 | B53: =B6*(1-'Datos Técnicos'!B6)^10 -> 475.55507 | C53: =INDEX('Datos Técnicos'!B20:Y23,E7,11)/100 -> 0.79 | D53: =B53*C53*'Datos Técnicos'!B5 -> 11420.93 | E53: =D53*B8 -> 1370.5117 | F53: =B53*B20/1000*'Datos Técnicos'!B5 -> 1662.5405 | G53: =F53*B9 -> 831.27025 | H53: =B13+B14 -> 0 | I53: =IF(B15>0,B6*B15*B7,0) -> 0 | J53: =G53+H53+I53 -> 831.27025 | K53: =E53-J53 -> 539.2414 | L53: =L52+K53 -> -1948.2534
A54: 12 | B54: =B6*(1-'Datos Técnicos'!B6)^11 -> 473.17729 | C54: =INDEX('Datos Técnicos'!B20:Y23,E7,12)/100 -> 0.74 | D54: =B54*C54*'Datos Técnicos'!B5 -> 10644.596 | E54: =D54*B8 -> 1277.3516 | F54: =B54*B20/1000*'Datos Técnicos'!B5 -> 1654.2278 | G54: =F54*B9 -> 827.1139 | H54: =B13+B14 -> 0 | I54: =IF(B15>0,B6*B15*B7,0) -> 0 | J54: =G54+H54+I54 -> 827.1139 | K54: =E54-J54 -> 450.23765 | L54: =L53+K54 -> -1498.0158
A55: 13 | B55: =B6*(1-'Datos Técnicos'!B6)^12 -> 470.8114 | C55: =INDEX('Datos Técnicos'!B20:Y23,E7,13)/100 -> 0.71 | D55: =B55*C55*'Datos Técnicos'!B5 -> 10161.993 | E55: =D55*B8 -> 1219.4392 | F55: =B55*B20/1000*'Datos Técnicos'!B5 -> 1645.9567 | G55: =F55*B9 -> 822.97833 | H55: =B13+B14 -> 0 | I55: =IF(B15>0,B6*B15*B7,0) -> 0 | J55: =G55+H55+I55 -> 822.97833 | K55: =E55-J55 -> 396.46087 | L55: =L54+K55 -> -1101.5549
A56: 14 | B56: =B6*(1-'Datos Técnicos'!B6)^13 -> 468.45735 | C56: =INDEX('Datos Técnicos'!B20:Y23,E7,14)/100 -> 0.68 | D56: =B56*C56*'Datos Técnicos'!B5 -> 9683.9503 | E56: =D56*B8 -> 1162.074 | F56: =B56*B20/1000*'Datos Técnicos'!B5 -> 1637.7269 | G56: =F56*B9 -> 818.86344 | H56: =B13+B14 -> 0 | I56: =IF(B15>0,B6*B15*B7,0) -> 0 | J56: =G56+H56+I56 -> 818.86344 | K56: =E56-J56 -> 343.21059 | L56: =L55+K56 -> -758.34434
A57: 15 | B57: =B6*(1-'Datos Técnicos'!B6)^14 -> 466.11506 | C57: =INDEX('Datos Técnicos'!B20:Y23,E7,15)/100 -> 0.64 | D57: =B57*C57*'Datos Técnicos'!B5 -> 9068.7346 | E57: =D57*B8 -> 1088.2482 | F57: =B57*B20/1000*'Datos Técnicos'!B5 -> 1629.5382 | G57: =F57*B9 -> 814.76912 | H57: =B13+B14 -> 0 | I57: =IF(B15>0,B6*B15*B7,0) -> 0 | J57: =G57+H57+I57 -> 814.76912 | K57: =E57-J57 -> 273.47903 | L57: =L56+K57 -> -484.86531
A58: 16 | B58: =B6*(1-'Datos Técnicos'!B6)^15 -> 463.78448 | C58: =INDEX('Datos Técnicos'!B20:Y23,E7,16)/100 -> 0.6 | D58: =B58*C58*'Datos Técnicos'!B5 -> 8459.429 | E58: =D58*B8 -> 1015.1315 | F58: =B58*B20/1000*'Datos Técnicos'!B5 -> 1621.3906 | G58: =F58*B9 -> 810.69528 | H58: =B13+B14 -> 0 | I58: =IF(B15>0,B6*B15*B7,0) -> 0 | J58: =G58+H58+I58 -> 810.69528 | K58: =E58-J58 -> 204.4362 | L58: =L57+K58 -> -280.42911
A59: 17 | B59: =B6*(1-'Datos Técnicos'!B6)^16 -> 461.46556 | C59: =INDEX('Datos Técnicos'!B20:Y23,E7,17)/100 -> 0.57 | D59: =B59*C59*'Datos Técnicos'!B5 -> 7996.2753 | E59: =D59*B8 -> 959.55303 | F59: =B59*B20/1000*'Datos Técnicos'!B5 -> 1613.2836 | G59: =F59*B9 -> 806.6418 | H59: =B13+B14 -> 0 | I59: =IF(B15>0,B6*B15*B7,0) -> 0 | J59: =G59+H59+I59 -> 806.6418 | K59: =E59-J59 -> 152.91123 | L59: =L58+K59 -> -127.51788
A60: 18 | B60: =B6*(1-'Datos Técnicos'!B6)^17 -> 459.15823 | C60: =INDEX('Datos Técnicos'!B20:Y23,E7,18)/100 -> 0.54 | D60: =B60*C60*'Datos Técnicos'!B5 -> 7537.5416 | E60: =D60*B8 -> 904.50499 | F60: =B60*B20/1000*'Datos Técnicos'!B5 -> 1605.2172 | G60: =F60*B9 -> 802.60859 | H60: =B13+B14 -> 0 | I60: =IF(B15>0,B6*B15*B7,0) -> 0 | J60: =G60+H60+I60 -> 802.60859 | K60: =E60-J60 -> 101.8964 | L60: =L59+K60 -> -25.621485
A61: 19 | B61: =B6*(1-'Datos Técnicos'!B6)^18 -> 456.86244 | C61: =INDEX('Datos Técnicos'!B20:Y23,E7,19)/100 -> 0.5 | D61: =B61*C61*'Datos Técnicos'!B5 -> 6944.3091 | E61: =D61*B8 -> 833.3171 | F61: =B61*B20/1000*'Datos Técnicos'!B5 -> 1597.1911 | G61: =F61*B9 -> 798.59555 | H61: =B13+B14 -> 0 | I61: =IF(B15>0,B6*B15*B7,0) -> 0 | J61: =G61+H61+I61 -> 798.59555 | K61: =E61-J61 -> 34.721546 | L61: =L60+K61 -> 9.1000605
A62: 20 | B62: =B6*(1-'Datos Técnicos'!B6)^19 -> 454.57813 | C62: =INDEX('Datos Técnicos'!B20:Y23,E7,20)/100 -> 0.47 | D62: =B62*C62*'Datos Técnicos'!B5 -> 6495.0123 | E62: =D62*B8 -> 779.40148 | F62: =B62*B20/1000*'Datos Técnicos'!B5 -> 1589.2051 | G62: =F62*B9 -> 794.60257 | H62: =B13+B14 -> 0 | I62: =IF(B15>0,B6*B15*B7,0) -> 0 | J62: =G62+H62+I62 -> 794.60257 | K62: =E62-J62 -> -15.201093 | L62: =L61+K62 -> -6.1010322
A63: 21 | B63: =B6*(1-'Datos Técnicos'!B6)^20 -> 452.30524 | C63: =INDEX('Datos Técnicos'!B20:Y23,E7,21)/100 -> 0.44 | D63: =B63*C63*'Datos Técnicos'!B5 -> 6050.0349 | E63: =D63*B8 -> 726.00419 | F63: =B63*B20/1000*'Datos Técnicos'!B5 -> 1581.2591 | G63: =F63*B9 -> 790.62956 | H63: =B13+B14 -> 0 | I63: =IF(B15>0,B6*B15*B7,0) -> 0 | J63: =G63+H63+I63 -> 790.62956 | K63: =E63-J63 -> -64.625373 | L63: =L62+K63 -> -70.726405
A64: 22 | B64: =B6*(1-'Datos Técnicos'!B6)^21 -> 450.04371 | C64: =INDEX('Datos Técnicos'!B20:Y23,E7,22)/100 -> 0.41 | D64: =B64*C64*'Datos Técnicos'!B5 -> 5609.3449 | E64: =D64*B8 -> 673.12138 | F64: =B64*B20/1000*'Datos Técnicos'!B5 -> 1573.3528 | G64: =F64*B9 -> 786.67641 | H64: =B13+B14 -> 0 | I64: =IF(B15>0,B6*B15*B7,0) -> 0 | J64: =G64+H64+I64 -> 786.67641 | K64: =E64-J64 -> -113.55503 | L64: =L63+K64 -> -184.28143
A65: 23 | B65: =B6*(1-'Datos Técnicos'!B6)^22 -> 447.7935 | C65: =INDEX('Datos Técnicos'!B20:Y23,E7,23)/100 -> 0.38 | D65: =B65*C65*'Datos Técnicos'!B5 -> 5172.9105 | E65: =D65*B8 -> 620.74926 | F65: =B65*B20/1000*'Datos Técnicos'!B5 -> 1565.4861 | G65: =F65*B9 -> 782.74303 | H65: =B13+B14 -> 0 | I65: =IF(B15>0,B6*B15*B7,0) -> 0 | J65: =G65+H65+I65 -> 782.74303 | K65: =E65-J65 -> -161.99377 | L65: =L64+K65 -> -346.27521
A66: 24 | B66: =B6*(1-'Datos Técnicos'!B6)^23 -> 445.55453 | C66: =INDEX('Datos Técnicos'!B20:Y23,E7,24)/100 -> 0.35 | D66: =B66*C66*'Datos Técnicos'!B5 -> 4740.7002 | E66: =D66*B8 -> 568.88402 | F66: =B66*B20/1000*'Datos Técnicos'!B5 -> 1557.6586 | G66: =F66*B9 -> 778.82931 | H66: =B13+B14 -> 0 | I66: =IF(B15>0,B6*B15*B7,0) -> 0 | J66: =G66+H66+I66 -> 778.82931 | K66: =E66-J66 -> -209.94529 | L66: =L65+K66 -> -556.2205

Sheet Cría y Venta
A1: AGROMACK | F1: Kit Avícola Profesional · Sistema de Gestión y Costeo
A2: CALCULADORA AVÍCOLA — MODO CRÍA Y VENTA
A3: Compra de pollitas de 1 día → venta como pollonas listas para postura
A5: DATOS DEL PROYECTO | D5: LÍNEA GENÉTICA (1, 2, 3 o 4)
A6: Número de pollitas | B6: 500 | D6: 1=Hy-Line Brown · 2=Lohmann Brown · 3=Hy-Line W-36 · 4=Lohmann LSL
A7: Precio pollita 1 día | B7: 1.2 | D7: Línea seleccionada | E7: 1
A8: Precio venta pollona | B8: 6.5
A9: Precio alimento recría / kg | B9: 0.45
A10: Costo construcción / m² | B10: 80
A11: Infraestructura adicional | B11: 500
A12: Vida útil infraestructura (meses) | B12: 120
A13: Mano de obra mensual | B13: 0
A14: Otros costos mensuales | B14: 0
A15: Semana de venta | B15: 17
A19: CÁLCULOS DEL CICLO DE CRÍA
A20: Área cría (m²) | B20: =B6*INDEX('Datos Técnicos'!I12:I15,E7) -> 30
A21: Mortalidad acum. recría (%) | B21: =1-(1-'Datos Técnicos'!B7)^B15 -> 0.049794169
A22: Aves estimadas al vender | B22: =B6*(1-B21) -> 475.10292
A23: Ingreso por venta | B23: =B22*B8 -> 3088.169
A24: Costo pollitas | B24: =B6*B7 -> 600
A25: Costo infraestructura | B25: =B20*B10+B11 -> 2900
A26: TOTAL INVERSIÓN INICIAL | B26: =B24+B25 -> 3500
A28: FLUJO MENSUAL PROYECTADO
A29: Alimento de recría por mes. El ingreso por venta se registra en el último mes.
A30: Mes | B30: Semanas | C30: Aves vivas | D30: Alimento kg (est.) | E30: Costo alimento | F30: Otros costos | G30: Ingreso venta | H30: Flujo neto | I30: Flujo acumulado
A31: 1 | B31: =IF(1>B15,"-",1&"–"&MIN(4,B15)) -> 1–4 | C31: =IF(1>B15,0,B6*(1-'Datos Técnicos'!B7)^MIN(4,B15)) -> 494.02695 | D31: =IF(1>B15,0,C31*AVERAGE(INDEX('Datos Técnicos'!B28:R29,IF(E7<=2,1,2),1):INDEX('Datos Técnicos'!B28:R29,IF(E7<=2,1,2),MIN(4,17)))*7*MIN(4,B15-1+1)/1000) -> 318.15335 | E31: =D31*B9 -> 143.16901 | F31: =IF(1>B15,0,B13+B14) -> 0 | G31: =IF(AND(1<=B15,MIN(4,B15)>=B15),C31*B8,0) -> 0 | H31: =G31-E31-F31 -> -143.16901 | I31: =-B26+H31 -> -3643.169
A32: 2 | B32: =IF(5>B15,"-",5&"–"&MIN(8,B15)) -> 5–8 | C32: =IF(5>B15,0,B6*(1-'Datos Técnicos'!B7)^MIN(8,B15)) -> 488.12525 | D32: =IF(5>B15,0,C32*AVERAGE(INDEX('Datos Técnicos'!B28:R29,IF(E7<=2,1,2),5):INDEX('Datos Técnicos'!B28:R29,IF(E7<=2,1,2),MIN(8,17)))*7*MIN(4,B15-5+1)/1000) -> 744.87913 | E32: =D32*B9 -> 335.19561 | F32: =IF(5>B15,0,B13+B14) -> 0 | G32: =IF(AND(5<=B15,MIN(8,B15)>=B15),C32*B8,0) -> 0 | H32: =G32-E32-F32 -> -335.19561 | I32: =I31+H32 -> -3978.3646
A33: 3 | B33: =IF(9>B15,"-",9&"–"&MIN(12,B15)) -> 9–12 | C33: =IF(9>B15,0,B6*(1-'Datos Técnicos'!B7)^MIN(12,B15)) -> 482.29405 | D33: =IF(9>B15,0,C33*AVERAGE(INDEX('Datos Técnicos'!B28:R29,IF(E7<=2,1,2),9):INDEX('Datos Técnicos'!B28:R29,IF(E7<=2,1,2),MIN(12,17)))*7*MIN(4,B15-9+1)/1000) -> 999.31327 | E33: =D33*B9 -> 449.69097 | F33: =IF(9>B15,0,B13+B14) -> 0 | G33: =IF(AND(9<=B15,MIN(12,B15)>=B15),C33*B8,0) -> 0 | H33: =G33-E33-F33 -> -449.69097 | I33: =I32+H33 -> -4428.0556
A34: 4 | B34: =IF(13>B15,"-",13&"–"&MIN(16,B15)) -> 13–16 | C34: =IF(13>B15,0,B6*(1-'Datos Técnicos'!B7)^MIN(16,B15)) -> 476.53251 | D34: =IF(13>B15,0,C34*AVERAGE(INDEX('Datos Técnicos'!B28:R29,IF(E7<=2,1,2),13):INDEX('Datos Técnicos'!B28:R29,IF(E7<=2,1,2),MIN(16,17)))*7*MIN(4,B15-13+1)/1000) -> 1200.8619 | E34: =D34*B9 -> 540.38787 | F34: =IF(13>B15,0,B13+B14) -> 0 | G34: =IF(AND(13<=B15,MIN(16,B15)>=B15),C34*B8,0) -> 0 | H34: =G34-E34-F34 -> -540.38787 | I34: =I33+H34 -> -4968.4435
A35: 5 | B35: =IF(17>B15,"-",17&"–"&MIN(20,B15)) -> 17–17 | C35: =IF(17>B15,0,B6*(1-'Datos Técnicos'!B7)^MIN(20,B15)) -> 475.10292 | D35: =IF(17>B15,0,C35*AVERAGE(INDEX('Datos Técnicos'!B28:R29,IF(E7<=2,1,2),17):INDEX('Datos Técnicos'!B28:R29,IF(E7<=2,1,2),MIN(20,17)))*7*MIN(4,B15-17+1)/1000) -> 332.57204 | E35: =D35*B9 -> 149.65742 | F35: =IF(17>B15,0,B13+B14) -> 0 | G35: =IF(AND(17<=B15,MIN(20,B15)>=B15),C35*B8,0) -> 3088.169 | H35: =G35-E35-F35 -> 2938.5115 | I35: =I34+H35 -> -2029.9319
A36: 6 | B36: =IF(21>B15,"-",21&"–"&MIN(24,B15)) -> - | C36: =IF(21>B15,0,B6*(1-'Datos Técnicos'!B7)^MIN(24,B15)) -> 0 | D36: 0 | E36: =D36*B9 -> 0 | F36: =IF(21>B15,0,B13+B14) -> 0 | G36: =IF(AND(21<=B15,MIN(24,B15)>=B15),C36*B8,0) -> 0 | H36: =G36-E36-F36 -> 0 | I36: =I35+H36 -> -2029.9319
A38: RESUMEN ECONÓMICO
A39: Inversión inicial | B39: =B26 -> 3500
A40: Ingreso total por venta | B40: =B23 -> 3088.169
A41: Margen bruto estimado | B41: =B40-B24-SUM(E31:E36)-SUM(F31:F36) -> 870.06808

Sheet Ciclo Completo
A1: AGROMACK | F1: Kit Avícola Profesional · Sistema de Gestión y Costeo
A2: CALCULADORA AVÍCOLA — CICLO COMPLETO
A3: Cría desde pollita de 1 día → postura hasta la pelecha
A5: DATOS DEL PROYECTO | D5: LÍNEA GENÉTICA (1, 2, 3 o 4)
A6: Número de pollitas | B6: 500 | D6: 1=Hy-Line Brown · 2=Lohmann Brown · 3=Hy-Line W-36 · 4=Lohmann LSL
A7: Precio pollita 1 día | B7: 1.2 | D7: Línea seleccionada | E7: 1
A8: Precio venta huevo / unidad | B8: 0.12 | D8: Sistema (1=Piso, 2=Jaula, 3=Semi-pastoreo) | E8: 1
A9: Precio alimento recría / kg | B9: 0.45 | D9: Comedero (1=Tolva, 2=Lineal) | E9: 1
A10: Precio alimento postura / kg | B10: 0.5 | D10: Bebedero (1=Nipple, 2=Campana, 3=Canal) | E10: 1
A11: Costo construcción / m² | B11: 80 | D11: Precio unitario comedero | E11: 18
A12: Infraestructura adicional | B12: 500 | D12: Precio unitario bebedero | E12: 1.2
A13: Vida útil infraestructura (meses) | B13: 120 | D13: Precio unitario nido | E13: 15
A14: Mano de obra mensual | B14: 0
A15: Otros costos mensuales | B15: 0
A16: Reposición aves postura (%/mes) | B16: 0
A19: DIMENSIONAMIENTO Y COSTOS
A20: Consumo postura g/ave/día | B20: =INDEX('Datos Técnicos'!D12:D15,E7) -> 115
A21: m²/ave postura | B21: =IF(E8=1,INDEX('Datos Técnicos'!F12:F15,E7),IF(E8=2,INDEX('Datos Técnicos'!G12:G15,E7),INDEX('Datos Técnicos'!H12:H15,E7))) -> 0.1
A22: Área requerida (m²) | B22: =B6*B21 -> 50
A23: Comederos requeridos | B23: =IF(E9=1,CEILING(B6/INDEX('Datos Técnicos'!K12:K15,E7),1),CEILING(B6*INDEX('Datos Técnicos'!J12:J15,E7)/100,1)) -> 17
A24: Bebederos requeridos | B24: =IF(E10=1,CEILING(B6/INDEX('Datos Técnicos'!L12:L15,E7),1),IF(E10=2,CEILING(B6/INDEX('Datos Técnicos'!M12:M15,E7),1),CEILING(B6*INDEX('Datos Técnicos'!N12:N15,E7)/100,1))) -> 63
A25: Nidos requeridos | B25: =CEILING(B6/INDEX('Datos Técnicos'!O12:O15,E7),1) -> 100
A26: Mortalidad acum. recría (%) | B26: =1-(1-'Datos Técnicos'!B7)^17 -> 0.049794169
A27: Aves al inicio postura | B27: =B6*(1-B26) -> 475.10292
A29: INVERSIÓN INICIAL
A30: Costo pollitas | B30: =B6*B7 -> 600
A31: Costo infraestructura | B31: =B22*B11+B12 -> 4500
A32: Costo comederos | B32: =B23*E11 -> 306
A33: Costo bebederos | B33: =B24*E12 -> 75.6
A34: Costo nidos | B34: =B25*E13 -> 1500
A35: TOTAL INVERSIÓN INICIAL | B35: =SUM(B30:B34) -> 6981.6
A36: Depreciación mensual infra | B36: =B31/B13 -> 37.5
A38: FLUJO MENSUAL PROYECTADO
A39: Fase ámbar = recría (sin ingresos). Fase verde = postura.
A40: Mes | B40: Fase | C40: Aves | D40: Postura/Sem. | E40: Huevos / Alim. kg | F40: Ingresos | G40: Egresos op. | H40: Flujo neto | I40: Flujo acumulado
A41: 1 | B41: Recría | C41: =B6*(1-'Datos Técnicos'!B7)^4 -> 494.02695 | D41: Sem. 1–4 | E41: =C41*AVERAGE(INDEX('Datos Técnicos'!B28:R29,IF(E7<=2,1,2),1):INDEX('Datos Técnicos'!B28:R29,IF(E7<=2,1,2),4))*7*4/1000 -> 318.15335 | F41: — | G41: =E41*B9+B14+B15 -> 143.16901 | H41: =-G41 -> -143.16901 | I41: =-B35+H41 -> -7124.769
A42: 2 | B42: Recría | C42: =B6*(1-'Datos Técnicos'!B7)^8 -> 488.12525 | D42: Sem. 5–8 | E42: =C42*AVERAGE(INDEX('Datos Técnicos'!B28:R29,IF(E7<=2,1,2),5):INDEX('Datos Técnicos'!B28:R29,IF(E7<=2,1,2),8))*7*4/1000 -> 744.87913 | F42: — | G42: =E42*B9+B14+B15 -> 335.19561 | H42: =-G42 -> -335.19561 | I42: =I41+H42 -> -7459.9646
A43: 3 | B43: Recría | C43: =B6*(1-'Datos Técnicos'!B7)^12 -> 482.29405 | D43: Sem. 9–12 | E43: =C43*AVERAGE(INDEX('Datos Técnicos'!B28:R29,IF(E7<=2,1,2),9):INDEX('Datos Técnicos'!B28:R29,IF(E7<=2,1,2),12))*7*4/1000 -> 999.31327 | F43: — | G43: =E43*B9+B14+B15 -> 449.69097 | H43: =-G43 -> -449.69097 | I43: =I42+H43 -> -7909.6556
A44: 4 | B44: Recría | C44: =B6*(1-'Datos Técnicos'!B7)^16 -> 476.53251 | D44: Sem. 13–16 | E44: =C44*AVERAGE(INDEX('Datos Técnicos'!B28:R29,IF(E7<=2,1,2),13):INDEX('Datos Técnicos'!B28:R29,IF(E7<=2,1,2),16))*7*4/1000 -> 1200.8619 | F44: — | G44: =E44*B9+B14+B15 -> 540.38787 | H44: =-G44 -> -540.38787 | I44: =I43+H44 -> -8450.0435
A45: 5 | B45: Postura | C45: =B27 -> 475.10292 | D45: =INDEX('Datos Técnicos'!B20:Y23,E7,1)/100 -> 0.62 | E45: =C45*D45*'Datos Técnicos'!B5 -> 8954.7398 | F45: =E45*B8 -> 1074.5688 | G45: =C45*B20/1000*'Datos Técnicos'!B5*B10+B14+B15+IF(B16>0,B6*B16*B7,0) -> 830.4799 | H45: =F45-G45 -> 244.08887 | I45: =I44+H45 -> -8205.9546
A46: 6 | B46: Postura | C46: =B27*(1-'Datos Técnicos'!B6)^1 -> 472.7274 | D46: =INDEX('Datos Técnicos'!B20:Y23,E7,2)/100 -> 0.92 | E46: =C46*D46*'Datos Técnicos'!B5 -> 13221.24 | F46: =E46*B8 -> 1586.5488 | G46: =C46*B20/1000*'Datos Técnicos'!B5*B10+B14+B15+IF(B16>0,B6*B16*B7,0) -> 826.3275 | H46: =F46-G46 -> 760.2213 | I46: =I45+H46 -> -7445.7333
A47: 7 | B47: Postura | C47: =B27*(1-'Datos Técnicos'!B6)^2 -> 470.36376 | D47: =INDEX('Datos Técnicos'!B20:Y23,E7,3)/100 -> 0.95 | E47: =C47*D47*'Datos Técnicos'!B5 -> 13584.106 | F47: =E47*B8 -> 1630.0927 | G47: =C47*B20/1000*'Datos Técnicos'!B5*B10+B14+B15+IF(B16>0,B6*B16*B7,0) -> 822.19586 | H47: =F47-G47 -> 807.8968 | I47: =I46+H47 -> -6637.8365
A48: 8 | B48: Postura | C48: =B27*(1-'Datos Técnicos'!B6)^3 -> 468.01195 | D48: =INDEX('Datos Técnicos'!B20:Y23,E7,4)/100 -> 0.95 | E48: =C48*D48*'Datos Técnicos'!B5 -> 13516.185 | F48: =E48*B8 -> 1621.9422 | G48: =C48*B20/1000*'Datos Técnicos'!B5*B10+B14+B15+IF(B16>0,B6*B16*B7,0) -> 818.08488 | H48: =F48-G48 -> 803.85732 | I48: =I47+H48 -> -5833.9792
A49: 9 | B49: Postura | C49: =B27*(1-'Datos Técnicos'!B6)^4 -> 465.67189 | D49: =INDEX('Datos Técnicos'!B20:Y23,E7,5)/100 -> 0.94 | E49: =C49*D49*'Datos Técnicos'!B5 -> 13307.04 | F49: =E49*B8 -> 1596.8448 | G49: =C49*B20/1000*'Datos Técnicos'!B5*B10+B14+B15+IF(B16>0,B6*B16*B7,0) -> 813.99446 | H49: =F49-G49 -> 782.85032 | I49: =I48+H49 -> -5051.1288
A50: 10 | B50: Postura | C50: =B27*(1-'Datos Técnicos'!B6)^5 -> 463.34353 | D50: =INDEX('Datos Técnicos'!B20:Y23,E7,6)/100 -> 0.93 | E50: =C50*D50*'Datos Técnicos'!B5 -> 13099.648 | F50: =E50*B8 -> 1571.9578 | G50: =C50*B20/1000*'Datos Técnicos'!B5*B10+B14+B15+IF(B16>0,B6*B16*B7,0) -> 809.92448 | H50: =F50-G50 -> 762.0333 | I50: =I49+H50 -> -4289.0956
A51: 11 | B51: Postura | C51: =B27*(1-'Datos Técnicos'!B6)^6 -> 461.02681 | D51: =INDEX('Datos Técnicos'!B20:Y23,E7,7)/100 -> 0.91 | E51: =C51*D51*'Datos Técnicos'!B5 -> 12753.846 | F51: =E51*B8 -> 1530.4615 | G51: =C51*B20/1000*'Datos Técnicos'!B5*B10+B14+B15+IF(B16>0,B6*B16*B7,0) -> 805.87486 | H51: =F51-G51 -> 724.58661 | I51: =I50+H51 -> -3564.5089
A52: 12 | B52: Postura | C52: =B27*(1-'Datos Técnicos'!B6)^7 -> 458.72167 | D52: =INDEX('Datos Técnicos'!B20:Y23,E7,8)/100 -> 0.89 | E52: =C52*D52*'Datos Técnicos'!B5 -> 12411.174 | F52: =E52*B8 -> 1489.3408 | G52: =C52*B20/1000*'Datos Técnicos'!B5*B10+B14+B15+IF(B16>0,B6*B16*B7,0) -> 801.84549 | H52: =F52-G52 -> 687.49535 | I52: =I51+H52 -> -2877.0136
A53: 13 | B53: Postura | C53: =B27*(1-'Datos Técnicos'!B6)^8 -> 456.42807 | D53: =INDEX('Datos Técnicos'!B20:Y23,E7,9)/100 -> 0.86 | E53: =C53*D53*'Datos Técnicos'!B5 -> 11932.855 | F53: =E53*B8 -> 1431.9426 | G53: =C53*B20/1000*'Datos Técnicos'!B5*B10+B14+B15+IF(B16>0,B6*B16*B7,0) -> 797.83626 | H53: =F53-G53 -> 634.10638 | I53: =I52+H53 -> -2242.9072
A54: 14 | B54: Postura | C54: =B27*(1-'Datos Técnicos'!B6)^9 -> 454.14593 | D54: =INDEX('Datos Técnicos'!B20:Y23,E7,10)/100 -> 0.83 | E54: =C54*D54*'Datos Técnicos'!B5 -> 11459.01 | F54: =E54*B8 -> 1375.0812 | G54: =C54*B20/1000*'Datos Técnicos'!B5*B10+B14+B15+IF(B16>0,B6*B16*B7,0) -> 793.84708 | H54: =F54-G54 -> 581.23412 | I54: =I53+H54 -> -1661.6731
A55: 15 | B55: Postura | C55: =B27*(1-'Datos Técnicos'!B6)^10 -> 451.8752 | D55: =INDEX('Datos Técnicos'!B20:Y23,E7,11)/100 -> 0.79 | E55: =C55*D55*'Datos Técnicos'!B5 -> 10852.235 | F55: =E55*B8 -> 1302.2682 | G55: =C55*B20/1000*'Datos Técnicos'!B5*B10+B14+B15+IF(B16>0,B6*B16*B7,0) -> 789.87784 | H55: =F55-G55 -> 512.39032 | I55: =I54+H55 -> -1149.2828
A56: 16 | B56: Postura | C56: =B27*(1-'Datos Técnicos'!B6)^11 -> 449.61582 | D56: =INDEX('Datos Técnicos'!B20:Y23,E7,12)/100 -> 0.74 | E56: =C56*D56*'Datos Técnicos'!B5 -> 10114.557 | F56: =E56*B8 -> 1213.7469 | G56: =C56*B20/1000*'Datos Técnicos'!B5*B10+B14+B15+IF(B16>0,B6*B16*B7,0) -> 785.92845 | H56: =F56-G56 -> 427.81845 | I56: =I55+H56 -> -721.46432
A57: 17 | B57: Postura | C57: =B27*(1-'Datos Técnicos'!B6)^12 -> 447.36774 | D57: =INDEX('Datos Técnicos'!B20:Y23,E7,13)/100 -> 0.71 | E57: =C57*D57*'Datos Técnicos'!B5 -> 9655.9853 | F57: =E57*B8 -> 1158.7182 | G57: =C57*B20/1000*'Datos Técnicos'!B5*B10+B14+B15+IF(B16>0,B6*B16*B7,0) -> 781.99881 | H57: =F57-G57 -> 376.71943 | I57: =I56+H57 -> -344.74489
A58: 18 | B58: Postura | C58: =B27*(1-'Datos Técnicos'!B6)^13 -> 445.1309 | D58: =INDEX('Datos Técnicos'!B20:Y23,E7,14)/100 -> 0.68 | E58: =C58*D58*'Datos Técnicos'!B5 -> 9201.746 | F58: =E58*B8 -> 1104.2095 | G58: =C58*B20/1000*'Datos Técnicos'!B5*B10+B14+B15+IF(B16>0,B6*B16*B7,0) -> 778.08882 | H58: =F58-G58 -> 326.1207 | I58: =I57+H58 -> -18.624185
A59: 19 | B59: Postura | C59: =B27*(1-'Datos Técnicos'!B6)^14 -> 442.90525 | D59: =INDEX('Datos Técnicos'!B20:Y23,E7,15)/100 -> 0.64 | E59: =C59*D59*'Datos Técnicos'!B5 -> 8617.1645 | F59: =E59*B8 -> 1034.0597 | G59: =C59*B20/1000*'Datos Técnicos'!B5*B10+B14+B15+IF(B16>0,B6*B16*B7,0) -> 774.19837 | H59: =F59-G59 -> 259.86137 | I59: =I58+H59 -> 241.23718
A60: 20 | B60: Postura | C60: =B27*(1-'Datos Técnicos'!B6)^15 -> 440.69072 | D60: =INDEX('Datos Técnicos'!B20:Y23,E7,16)/100 -> 0.6 | E60: =C60*D60*'Datos Técnicos'!B5 -> 8038.1988 | F60: =E60*B8 -> 964.58385 | G60: =C60*B20/1000*'Datos Técnicos'!B5*B10+B14+B15+IF(B16>0,B6*B16*B7,0) -> 770.32738 | H60: =F60-G60 -> 194.25647 | I60: =I59+H60 -> 435.49365
A61: 21 | B61: Postura | C61: =B27*(1-'Datos Técnicos'!B6)^16 -> 438.48727 | D61: =INDEX('Datos Técnicos'!B20:Y23,E7,17)/100 -> 0.57 | E61: =C61*D61*'Datos Técnicos'!B5 -> 7598.1074 | F61: =E61*B8 -> 911.77289 | G61: =C61*B20/1000*'Datos Técnicos'!B5*B10+B14+B15+IF(B16>0,B6*B16*B7,0) -> 766.47574 | H61: =F61-G61 -> 145.29714 | I61: =I60+H61 -> 580.79079
A62: 22 | B62: Postura | C62: =B27*(1-'Datos Técnicos'!B6)^17 -> 436.29483 | D62: =INDEX('Datos Técnicos'!B20:Y23,E7,18)/100 -> 0.54 | E62: =C62*D62*'Datos Técnicos'!B5 -> 7162.216 | F62: =E62*B8 -> 859.46591 | G62: =C62*B20/1000*'Datos Técnicos'!B5*B10+B14+B15+IF(B16>0,B6*B16*B7,0) -> 762.64337 | H62: =F62-G62 -> 96.822549 | I62: =I61+H62 -> 677.61334
A63: 23 | B63: Postura | C63: =B27*(1-'Datos Técnicos'!B6)^18 -> 434.11336 | D63: =INDEX('Datos Técnicos'!B20:Y23,E7,19)/100 -> 0.5 | E63: =C63*D63*'Datos Técnicos'!B5 -> 6598.523 | F63: =E63*B8 -> 791.82276 | G63: =C63*B20/1000*'Datos Técnicos'!B5*B10+B14+B15+IF(B16>0,B6*B16*B7,0) -> 758.83015 | H63: =F63-G63 -> 32.992615 | I63: =I62+H63 -> 710.60596
A64: 24 | B64: Postura | C64: =B27*(1-'Datos Técnicos'!B6)^19 -> 431.94279 | D64: =INDEX('Datos Técnicos'!B20:Y23,E7,20)/100 -> 0.47 | E64: =C64*D64*'Datos Técnicos'!B5 -> 6171.5986 | F64: =E64*B8 -> 740.59183 | G64: =C64*B20/1000*'Datos Técnicos'!B5*B10+B14+B15+IF(B16>0,B6*B16*B7,0) -> 755.036 | H64: =F64-G64 -> -14.444167 | I64: =I63+H64 -> 696.16179
A65: 25 | B65: Postura | C65: =B27*(1-'Datos Técnicos'!B6)^20 -> 429.78308 | D65: =INDEX('Datos Técnicos'!B20:Y23,E7,21)/100 -> 0.44 | E65: =C65*D65*'Datos Técnicos'!B5 -> 5748.7784 | F65: =E65*B8 -> 689.85341 | G65: =C65*B20/1000*'Datos Técnicos'!B5*B10+B14+B15+IF(B16>0,B6*B16*B7,0) -> 751.26082 | H65: =F65-G65 -> -61.407406 | I65: =I64+H65 -> 634.75438
A66: 26 | B66: Postura | C66: =B27*(1-'Datos Técnicos'!B6)^21 -> 427.63416 | D66: =INDEX('Datos Técnicos'!B20:Y23,E7,22)/100 -> 0.41 | E66: =C66*D66*'Datos Técnicos'!B5 -> 5330.0322 | F66: =E66*B8 -> 639.60386 | G66: =C66*B20/1000*'Datos Técnicos'!B5*B10+B14+B15+IF(B16>0,B6*B16*B7,0) -> 747.50451 | H66: =F66-G66 -> -107.90065 | I66: =I65+H66 -> 526.85373
A67: 27 | B67: Postura | C67: =B27*(1-'Datos Técnicos'!B6)^22 -> 425.49599 | D67: =INDEX('Datos Técnicos'!B20:Y23,E7,23)/100 -> 0.38 | E67: =C67*D67*'Datos Técnicos'!B5 -> 4915.3297 | F67: =E67*B8 -> 589.83956 | G67: =C67*B20/1000*'Datos Técnicos'!B5*B10+B14+B15+IF(B16>0,B6*B16*B7,0) -> 743.76699 | H67: =F67-G67 -> -153.92743 | I67: =I66+H67 -> 372.9263
A68: 28 | B68: Postura | C68: =B27*(1-'Datos Técnicos'!B6)^23 -> 423.36851 | D68: =INDEX('Datos Técnicos'!B20:Y23,E7,24)/100 -> 0.35 | E68: =C68*D68*'Datos Técnicos'!B5 -> 4504.641 | F68: =E68*B8 -> 540.55691 | G68: =C68*B20/1000*'Datos Técnicos'!B5*B10+B14+B15+IF(B16>0,B6*B16*B7,0) -> 740.04816 | H68: =F68-G68 -> -199.49124 | I68: =I67+H68 -> 173.43506

Sheet Datos Técnicos
A1: AGROMACK | N1: Kit Avícola Profesional · Sistema de Gestión y Costeo
A2: DATOS TÉCNICOS Y CURVAS DE REFERENCIA
A4: Constantes
A5: Días promedio por mes | B5: 30.4
A6: Mortalidad mensual postura (%) | B6: 0.005
A7: Mortalidad semanal recría (%) | B7: 0.003
A8: Semanas de recría estándar | B8: 17
A10: Parámetros por línea genética
A11: Línea | B11: Tipo | C11: Aprox. | D11: Consumo g/día | E11: Agua ratio | F11: m²/ave piso | G11: m²/ave jaula | H11: m²/ave semi | I11: m²/ave cría | J11: Comedero cm | K11: Aves/tolva | L11: Aves/nipple | M11: Aves/campana | N11: Bebedero cm | O11: Aves/nido | P11: Postura prom % | Q11: Postura pico % | R11: Sem. pelecha
A12: Hy-Line Brown | B12: Café | C12: No | D12: 115 | E12: 1.8 | F12: 0.1 | G12: 0.055 | H12: 0.25 | I12: 0.06 | J12: 10 | K12: 30 | L12: 8 | M12: 80 | N12: 10 | O12: 5 | P12: 92 | Q12: 96 | R12: 72
A13: Lohmann Brown | B13: Café | C13: Sí | D13: 115 | E13: 1.8 | F13: 0.1 | G13: 0.055 | H13: 0.25 | I13: 0.06 | J13: 10 | K13: 30 | L13: 8 | M13: 80 | N13: 10 | O13: 5 | P13: 92 | Q13: 96 | R13: 72
A14: Hy-Line W-36 | B14: Blanco | C14: No | D14: 100 | E14: 1.8 | F14: 0.09 | G14: 0.045 | H14: 0.22 | I14: 0.055 | J14: 10 | K14: 30 | L14: 8 | M14: 80 | N14: 10 | O14: 5 | P14: 93 | Q14: 97 | R14: 74
A15: Lohmann LSL | B15: Blanco | C15: Sí | D15: 100 | E15: 1.8 | F15: 0.09 | G15: 0.045 | H15: 0.22 | I15: 0.055 | J15: 10 | K15: 30 | L15: 8 | M15: 80 | N15: 10 | O15: 5 | P15: 93 | Q15: 97 | R15: 74
A18: Curvas de postura mensual (%)
A19: Línea | B19: Mes 1 | C19: Mes 2 | D19: Mes 3 | E19: Mes 4 | F19: Mes 5 | G19: Mes 6 | H19: Mes 7 | I19: Mes 8 | J19: Mes 9 | K19: Mes 10 | L19: Mes 11 | M19: Mes 12 | N19: Mes 13 | O19: Mes 14 | P19: Mes 15 | Q19: Mes 16 | R19: Mes 17 | S19: Mes 18 | T19: Mes 19 | U19: Mes 20 | V19: Mes 21 | W19: Mes 22 | X19: Mes 23 | Y19: Mes 24
A20: Hy-Line Brown | B20: 62 | C20: 92 | D20: 95 | E20: 95 | F20: 94 | G20: 93 | H20: 91 | I20: 89 | J20: 86 | K20: 83 | L20: 79 | M20: 74 | N20: 71 | O20: 68 | P20: 64 | Q20: 60 | R20: 57 | S20: 54 | T20: 50 | U20: 47 | V20: 44 | W20: 41 | X20: 38 | Y20: 35
A21: Lohmann Brown | B21: 60 | C21: 91 | D21: 94 | E21: 95 | F21: 94 | G21: 92 | H21: 90 | I21: 88 | J21: 85 | K21: 82 | L21: 78 | M21: 74 | N21: 70 | O21: 67 | P21: 63 | Q21: 59 | R21: 56 | S21: 53 | T21: 50 | U21: 47 | V21: 44 | W21: 41 | X21: 38 | Y21: 35
A22: Hy-Line W-36 | B22: 64 | C22: 93 | D22: 96 | E22: 96 | F22: 95 | G22: 94 | H22: 92 | I22: 90 | J22: 87 | K22: 84 | L22: 80 | M22: 76 | N22: 73 | O22: 69 | P22: 66 | Q22: 62 | R22: 58 | S22: 55 | T22: 52 | U22: 49 | V22: 46 | W22: 43 | X22: 40 | Y22: 37
A23: Lohmann LSL | B23: 63 | C23: 92 | D23: 96 | E23: 96 | F23: 95 | G23: 93 | H23: 91 | I23: 89 | J23: 86 | K23: 83 | L23: 79 | M23: 75 | N23: 72 | O23: 68 | P23: 65 | Q23: 61 | R23: 58 | S23: 54 | T23: 51 | U23: 48 | V23: 45 | W23: 42 | X23: 39 | Y23: 36
A26: Consumo recría g/ave/día por semana
A27: Tipo | B27: Sem 1 | C27: Sem 2 | D27: Sem 3 | E27: Sem 4 | F27: Sem 5 | G27: Sem 6 | H27: Sem 7 | I27: Sem 8 | J27: Sem 9 | K27: Sem 10 | L27: Sem 11 | M27: Sem 12 | N27: Sem 13 | O27: Sem 14 | P27: Sem 15 | Q27: Sem 16 | R27: Sem 17
A28: Café (Hy-Line Brown / Lohmann Brown) | B28: 10 | C28: 18 | D28: 28 | E28: 36 | F28: 44 | G28: 52 | H28: 58 | I28: 64 | J28: 68 | K28: 72 | L28: 76 | M28: 80 | N28: 84 | O28: 88 | P28: 92 | Q28: 96 | R28: 100
A29: Blanco (Hy-Line W-36 / Lohmann LSL) | B29: 10 | C29: 17 | D29: 26 | E29: 34 | F29: 42 | G29: 49 | H29: 55 | I29: 60 | J29: 64 | K29: 68 | L29: 72 | M29: 75 | N29: 78 | O29: 81 | P29: 84 | Q29: 87 | R29: 90
A31: Las curvas Lohmann son aproximaciones conservadoras, no datos oficiales del fabricante.
